django_webserver/__init__.py
django_webserver/base_command.py
django_webserver/utils.py
django_webserver/management/__init__.py
django_webserver/management/commands/__init__.py
django_webserver/management/commands/gunicorn.py
django_webserver/management/commands/pyuwsgi.py
django_webserver/management/commands/uvicorn.py
django_webserver/management/commands/waitress.py
django_webserver/tests/__init__.py
django_webserver/tests/app.py
django_webserver/tests/django_settings.py
django_webserver/tests/tests.py
django_webserver-1.2.0.dist-info/LICENSE
django_webserver-1.2.0.dist-info/WHEEL
django_webserver-1.2.0.dist-info/METADATA
django_webserver-1.2.0.dist-info/RECORD
