Metadata-Version: 1.1
Name: django-webserver
Version: 1.2.0
Summary: Django management commands for production webservers
Home-page: https://github.com/lincolnloop/django-webserver
Author: Peter Baumgartner
Author-email: pete@lincolnloop.com
